yunexpress_lib/__init__.py
yunexpress_lib/error.py
yunexpress_lib/tracking.py
carrier.yunexpress-2021.2.1.dist-info/WHEEL
carrier.yunexpress-2021.2.1.dist-info/METADATA
carrier.yunexpress-2021.2.1.dist-info/RECORD
